{"hero":{"kicker":"Career · Ansiversa mini app","title":"Proposal Writer","description":"Generate structured proposals quickly from a clear purpose and supporting details.","points":["Structured proposals","Quick generation","Clear proposal sections"],"primaryAction":{"label":"Explore Proposal Writer","path":"/proposal-writer"}},"flow":{"kicker":"Writing flow","title":"Describe → Generate → Review","steps":["Describe the proposal need","Generate a structured proposal","Review the proposal sections"]},"stats":[{"label":"Output","value":"Proposal"},{"label":"Structure","value":"Clear"},{"label":"Generation","value":"Quick"}],"timeline":null,"differences":{"title":"Move from proposal intent to a structured draft","description":"Proposal Writer focuses on generating proposals with clear, reviewable sections.","items":[{"kicker":"Pillar 01","title":"Proposal context","description":"Begin with the purpose and relevant details."},{"kicker":"Pillar 02","title":"Structured generation","description":"Create a proposal organized into clear sections."},{"kicker":"Pillar 03","title":"Draft review","description":"Review the generated proposal before using it."}]},"feel":{"kicker":"How it feels","title":"A clear starting point for proposal writing","description":"The workflow reduces blank-page effort while keeping the proposal structured.","items":[{"title":"Describe the need","description":"Provide the purpose and supporting information."},{"title":"Generate the proposal","description":"Create a structured draft quickly."},{"title":"Review the sections","description":"Check the proposal before using it."}]},"audiences":{"title":"Who uses Proposal Writer","description":"Useful for people preparing structured proposals.","items":[{"title":"Freelancers","description":"Prepare proposals for potential client work."},{"title":"Professionals","description":"Create structured proposals for business needs."},{"title":"Small businesses","description":"Develop clear proposal drafts quickly."}]},"resourceSection":{"title":"Proposal-writing essentials","description":"Keep the proposal purpose, structure, and review connected.","items":[{"title":"Proposal context","description":"Describe what the proposal should address."},{"title":"Structured draft","description":"Generate clear proposal sections."},{"title":"Final review","description":"Check the proposal before using it."}]},"groupedSection":{"title":"Build a structured proposal","description":"Move from proposal context toward a reviewable draft.","groups":[{"kicker":"Define","title":"Set the proposal context","items":[{"name":"Purpose","description":"Clarify what the proposal should achieve."},{"name":"Details","description":"Provide the relevant supporting information."}]},{"kicker":"Draft","title":"Generate and review","items":[{"name":"Structure","description":"Create clear proposal sections."},{"name":"Review","description":"Check the complete proposal draft."}]}]},"technicalSection":{"title":"Designed for structured proposal generation","description":"Proposal Writer follows the shared Ansiversa mini-app architecture.","items":["API-driven overview metadata.","Proposal-context and structured-draft-ready workflow.","Responsive presentation across devices."]},"finalCta":{"title":"Explore structured proposal writing","description":"Visit Proposal Writer to review its planned proposal-generation experience.","action":{"label":"Explore Proposal Writer","path":"/proposal-writer"}}}