{"hero":{"kicker":"Personal Finance · Ansiversa mini app","title":"Savings Goal Planner","description":"Track private fixed-currency savings targets, contributions, milestones, and transparent deadline pace.","points":["Contribution and correction history","Goal milestones","Per-currency summaries"],"primaryAction":{"label":"Explore","path":"/savings-goal-planner/goals"}},"flow":{"kicker":"Workflow","title":"Plan → Record → Progress","steps":["Create a target and starting balance","Record contributions or corrections","Review milestones and required pace"]},"stats":[{"label":"Precision","value":"Decimal"},{"label":"Currencies","value":"Separated"},{"label":"Access","value":"Authenticated"}],"timeline":null,"differences":{"title":"Savings planning without financial overreach","description":"User-entered records remain transparent and private.","items":[{"kicker":"Goals","title":"Define the target","description":"Set category, currency, amount, priority, and optional date."},{"kicker":"History","title":"Explain every change","description":"Record contributions, withdrawals, and corrections."},{"kicker":"Pace","title":"See what remains","description":"Review deterministic weekly and monthly planning pace."}]},"feel":{"kicker":"How it feels","title":"Clear, calm, and accountable","description":"Simple records make long-term targets easier to revisit.","items":[{"title":"Accurate","description":"Decimal arithmetic recalculates every mutation."},{"title":"Understandable","description":"Percentage text accompanies visual progress."},{"title":"Bounded","description":"No banking, transfers, investment predictions, or financial advice."}]},"audiences":{"title":"Who uses Savings Goal Planner","description":"For people building a personal savings target.","items":[{"title":"Individuals","description":"Track an emergency fund or planned purchase."},{"title":"Families","description":"Plan education, wedding, or family costs."},{"title":"Travellers and makers","description":"Save toward travel or a personal project."}]},"resourceSection":{"title":"Savings essentials","description":"A complete planning record.","items":[{"title":"Goals","description":"Target, starting balance, deadline, priority, and state."},{"title":"Transactions","description":"Dated contribution and correction history."},{"title":"Milestones","description":"Derived reached, pending, and missed stages."}]},"groupedSection":{"title":"Progress without misleading totals","description":"Currencies and states stay explicit.","groups":[{"kicker":"Record","title":"Maintain the plan","items":[{"name":"Balance","description":"Negative balances and overfunding are rejected."},{"name":"Status","description":"Full funding completes active goals automatically."}]},{"kicker":"Review","title":"Find what needs attention","items":[{"name":"Filters","description":"Combine status, category, priority, currency, timing, and dates."},{"name":"Dashboard","description":"Amounts remain grouped by currency."}]}]},"technicalSection":{"title":"Private and owner scoped","description":"An isolated database and protected nested APIs keep each user’s plans separate.","items":["Three cascade-linked application tables.","Two-decimal half-up authoritative arithmetic.","Archived goals are read-only and inactive states are excluded from currency totals."]},"finalCta":{"title":"Plan a savings target","description":"Open the protected goals workflow.","action":{"label":"Explore","path":"/savings-goal-planner/goals"}}}
